pystdf4/__init__.py
pystdf4/Core/__init__.py
pystdf4/Core/data_base.py
pystdf4/Core/data_type.py
pystdf4/Core/dynamic_buffer.py
pystdf4/Core/mixins.py
pystdf4/IO/__init__.py
pystdf4/IO/base.py
pystdf4/IO/stdf4reader.py
pystdf4/IO/stdf4writer.py
pystdf4/Records/__init__.py
pystdf4/Records/base.py
pystdf4/Records/literials.py
pystdf4/Records/packer.py
pystdf4-0.1.2.dist-info/licenses/LICENSE
pystdf4-0.1.2.dist-info/METADATA
pystdf4-0.1.2.dist-info/WHEEL
pystdf4-0.1.2.dist-info/top_level.txt
pystdf4-0.1.2.dist-info/RECORD
