Metadata-Version: 2.4
Name: pystdf4
Version: 0.1.2
Summary: A Python library for reading and writing STDF4 files
Author-email: YQZhu <asa_choo@hotmail.com>
License: MIT License
Project-URL: Homepage, https://github.com/Asachoo/pystdf4
Project-URL: Documentation, https://github.com/Asachoo/pystdf4
Project-URL: Source, https://github.com/Asachoo/pystdf4
Project-URL: Issues, https://github.com/Asachoo/pystdf4/issues
Keywords: engineering,electronics,automatic-test-equipment,ate,standard-test-data-format,stdf
Classifier: Development Status :: 3 - Alpha
Classifier: Programming Language :: Python :: 3
Classifier: Programming Language :: Python :: 3.8
Classifier: Programming Language :: Python :: 3.9
Classifier: Programming Language :: Python :: 3.10
Classifier: Programming Language :: Python :: 3.11
Classifier: Programming Language :: Python :: 3.12
Classifier: Programming Language :: Python :: 3.13
Classifier: Programming Language :: Python :: 3.14
Classifier: License :: OSI Approved :: MIT License
Classifier: Operating System :: OS Independent
Classifier: Topic :: Scientific/Engineering
Classifier: Topic :: Scientific/Engineering :: Electronic Design Automation (EDA)
Classifier: Topic :: Software Development :: Libraries
Classifier: Topic :: Software Development :: Libraries :: Python Modules
Requires-Python: >=3.8
License-File: LICENSE
Dynamic: license-file
